CytoSmartOpenAPI/__init__.py
CytoSmartOpenAPI/cytosmart_device.py
CytoSmartOpenAPI/listener.py
CytoSmartOpenAPI/main.py
CytoSmartOpenAPI/CytoSmartApp/Azure.Core.dll
CytoSmartOpenAPI/CytoSmartApp/Azure.Storage.Blobs.dll
CytoSmartOpenAPI/CytoSmartApp/Azure.Storage.Common.dll
CytoSmartOpenAPI/CytoSmartApp/Camera.dll
CytoSmartOpenAPI/CytoSmartApp/Camera.pdb
CytoSmartOpenAPI/CytoSmartApp/CytoSmart.Logic.CellCounter.dll
CytoSmartOpenAPI/CytoSmartApp/CytoSmart.Logic.CellCounter.pdb
CytoSmartOpenAPI/CytoSmartApp/CytoSmart.Logic.Lux.dll
CytoSmartOpenAPI/CytoSmartApp/CytoSmart.Logic.Lux.pdb
CytoSmartOpenAPI/CytoSmartApp/CytoSmart.Logic.Omni.Common.dll
CytoSmartOpenAPI/CytoSmartApp/CytoSmart.Logic.Omni.Common.pdb
CytoSmartOpenAPI/CytoSmartApp/CytoSmart.Logic.Omni.RobotArm.dll
CytoSmartOpenAPI/CytoSmartApp/CytoSmart.Logic.Omni.RobotArm.pdb
CytoSmartOpenAPI/CytoSmartApp/CytoSmart.Logic.Omni.dll
CytoSmartOpenAPI/CytoSmartApp/CytoSmart.Logic.Omni.pdb
CytoSmartOpenAPI/CytoSmartApp/CytoSmart.Services.CellCounter.dll
CytoSmartOpenAPI/CytoSmartApp/CytoSmart.Services.CellCounter.pdb
CytoSmartOpenAPI/CytoSmartApp/CytoSmart.Services.Common.dll
CytoSmartOpenAPI/CytoSmartApp/CytoSmart.Services.Common.pdb
CytoSmartOpenAPI/CytoSmartApp/CytoSmart.Services.Lux.dll
CytoSmartOpenAPI/CytoSmartApp/CytoSmart.Services.Lux.pdb
CytoSmartOpenAPI/CytoSmartApp/CytoSmart.Services.Omni.dll
CytoSmartOpenAPI/CytoSmartApp/CytoSmart.Services.Omni.pdb
CytoSmartOpenAPI/CytoSmartApp/CytoSmartService.exe
CytoSmartOpenAPI/CytoSmartApp/CytoSmartService.exe.config
CytoSmartOpenAPI/CytoSmartApp/CytoSmartService.pdb
CytoSmartOpenAPI/CytoSmartApp/Device.Core.dll
CytoSmartOpenAPI/CytoSmartApp/Device.Core.pdb
CytoSmartOpenAPI/CytoSmartApp/Device.dll
CytoSmartOpenAPI/CytoSmartApp/Device.pdb
CytoSmartOpenAPI/CytoSmartApp/FirmwareUpdate_MD_VC140_v3_2_IDS.dll
CytoSmartOpenAPI/CytoSmartApp/GCBase_MD_VC140_v3_2_IDS.dll
CytoSmartOpenAPI/CytoSmartApp/GenApi_MD_VC140_v3_2_IDS.dll
CytoSmartOpenAPI/CytoSmartApp/ImageAlgorithms.dll
CytoSmartOpenAPI-1.3.0.dist-info/LICENSE
CytoSmartOpenAPI-1.3.0.dist-info/METADATA
CytoSmartOpenAPI-1.3.0.dist-info/WHEEL
CytoSmartOpenAPI-1.3.0.dist-info/entry_points.txt
CytoSmartOpenAPI-1.3.0.dist-info/top_level.txt
CytoSmartOpenAPI-1.3.0.dist-info/RECORD
